[
  {
    "segment": "stress",
    "n_contracts": 32104,
    "total_debt": 1576113408.0,
    "available_limit": 6546221056.0,
    "payment_sum_1m": 74906608.0,
    "pdn_current": 0.2914404571056366,
    "dpd": 0.31138495631536783,
    "utilization": 0.4042171835899353,
    "default_rate": 0.030436996054532796
  },
  {
    "segment": "growing",
    "n_contracts": 16729,
    "total_debt": 4345702912.0,
    "available_limit": 560664320.0,
    "payment_sum_1m": 1184199168.0,
    "pdn_current": 0.4123048186302185,
    "dpd": 5.8596038907769834e-05,
    "utilization": 0.9458298087120056,
    "default_rate": 0.000996132661432087
  },
  {
    "segment": "stable",
    "n_contracts": 15771,
    "total_debt": 365420000.0,
    "available_limit": 1743178752.0,
    "payment_sum_1m": 439277216.0,
    "pdn_current": 0.18468651175498962,
    "dpd": 0.4185904888445995,
    "utilization": 0.15464738011360168,
    "default_rate": 0.00013840447323257488
  },
  {
    "segment": "delinquent",
    "n_contracts": 5562,
    "total_debt": 2019723648.0,
    "available_limit": 28282754.0,
    "payment_sum_1m": 2479815.5,
    "pdn_current": 0.7144051790237427,
    "dpd": 200.72201399571028,
    "utilization": 0.9710243940353394,
    "default_rate": 0.9979201421236216
  }
]